data/docs/nova/migration_guidelines.txt
data/docs/nova/general/bring_focus_to_sections.txt
data/docs/nova/general/chain_of_thought_prompting.txt
data/docs/nova/general/creating_precise_prompts.txt
data/docs/nova/general/few_shot_prompting.txt
data/docs/nova/general/provide_supporting_text.txt
data/docs/nova/general/requiring_structured_output.txt
data/docs/nova/general/system_role.txt
data/prompts/prompt_nova_migration.txt
data/prompts/prompt_nova_migration_system.txt
nova_meta_prompter/__init__.py
nova_meta_prompter/transform.py
nova_meta_prompter-0.1.3.dist-info/METADATA
nova_meta_prompter-0.1.3.dist-info/WHEEL
nova_meta_prompter-0.1.3.dist-info/top_level.txt
nova_meta_prompter-0.1.3.dist-info/RECORD
