Metadata-Version: 2.4
Name: nova-meta-prompter
Version: 0.1.3
Summary: Transform prompts to align with Amazon Nova guidelines
Author-email: Arlind Nocaj <arlind.nocaj@gmail.com>
License: MIT
Requires-Python: >=3.8
Requires-Dist: boto3>=1.26.0
Provides-Extra: dev
Requires-Dist: pytest>=7.0.0; extra == "dev"
Requires-Dist: pytest-mock>=3.10.0; extra == "dev"
Requires-Dist: jupyter>=1.1.1; extra == "dev"
Requires-Dist: build>=1.0.0; extra == "dev"
Requires-Dist: twine>=4.0.0; extra == "dev"
Requires-Dist: poethepoet>=0.24.0; extra == "dev"
